[
    {
        "id": 1,
        "nome":"Naruto Uzumaki",
        "email":"naruto@teste.com",
        "senha":"$2b$10$f9ElcnNIDjjG6GDx/qX8VOepwk7bPB.I01tEiwA9OSR7AJptx6KtW"
    },
    {
        "id": 2,
        "nome":"Sasuke Uchiha",
        "email":"sasuke@teste.com",
        "senha":"$2b$10$f9ElcnNIDjjG6GDx/qX8VOepwk7bPB.I01tEiwA9OSR7AJptx6KtW"
    },
    {
        "id": 3,
        "nome":"Sakura Haruno",
        "email":"sakura@teste.com",
        "senha":"$2b$10$f9ElcnNIDjjG6GDx/qX8VOepwk7bPB.I01tEiwA9OSR7AJptx6KtW"
    }
]